gsmls.py
gsmls-0.0.4.dist-info/LICENSE
gsmls-0.0.4.dist-info/METADATA
gsmls-0.0.4.dist-info/WHEEL
gsmls-0.0.4.dist-info/top_level.txt
gsmls-0.0.4.dist-info/RECORD
