Metadata-Version: 2.1
Name: gsmls
Version: 0.0.4
Summary: Python wrapper for gsmls.
Home-page: https://github.com/AlJohri/gsmls
Author: Al Johri
Author-email: al.johri@gmail.com
License: MIT
Platform: UNKNOWN
Classifier: Programming Language :: Python :: 3 :: Only
Classifier: Programming Language :: Python :: 3.6
Classifier: License :: OSI Approved :: MIT License
Requires-Dist: requests
Requires-Dist: cssselect
Requires-Dist: lxml
